[
  {
    "x": 32,
    "y": 32,
    "density": 75
  },
  {
    "x": 32,
    "y": 96,
    "density": 90
  },
  {
    "x": 32,
    "y": 160,
    "density": 78
  },
  {
    "x": 32,
    "y": 224,
    "density": 76
  },
  {
    "x": 32,
    "y": 288,
    "density": 90
  },
  {
    "x": 32,
    "y": 352,
    "density": 71
  },
  {
    "x": 32,
    "y": 416,
    "density": 84
  },
  {
    "x": 32,
    "y": 480,
    "density": 73
  },
  {
    "x": 32,
    "y": 544,
    "density": 71
  },
  {
    "x": 32,
    "y": 608,
    "density": 81
  },
  {
    "x": 32,
    "y": 672,
    "density": 65
  },
  {
    "x": 32,
    "y": 736,
    "density": 66
  },
  {
    "x": 96,
    "y": 32,
    "density": 62
  },
  {
    "x": 96,
    "y": 96,
    "density": 64
  },
  {
    "x": 96,
    "y": 160,
    "density": 67
  },
  {
    "x": 96,
    "y": 224,
    "density": 60
  },
  {
    "x": 96,
    "y": 288,
    "density": 68
  },
  {
    "x": 96,
    "y": 352,
    "density": 88
  },
  {
    "x": 96,
    "y": 416,
    "density": 69
  },
  {
    "x": 96,
    "y": 480,
    "density": 62
  },
  {
    "x": 96,
    "y": 544,
    "density": 80
  },
  {
    "x": 96,
    "y": 608,
    "density": 66
  },
  {
    "x": 96,
    "y": 672,
    "density": 77
  },
  {
    "x": 96,
    "y": 736,
    "density": 75
  },
  {
    "x": 160,
    "y": 32,
    "density": 90
  },
  {
    "x": 160,
    "y": 96,
    "density": 67
  },
  {
    "x": 160,
    "y": 160,
    "density": 74
  },
  {
    "x": 160,
    "y": 224,
    "density": 92
  },
  {
    "x": 160,
    "y": 288,
    "density": 97
  },
  {
    "x": 160,
    "y": 352,
    "density": 83
  },
  {
    "x": 160,
    "y": 416,
    "density": 98
  },
  {
    "x": 160,
    "y": 480,
    "density": 90
  },
  {
    "x": 160,
    "y": 544,
    "density": 73
  },
  {
    "x": 160,
    "y": 608,
    "density": 85
  },
  {
    "x": 160,
    "y": 672,
    "density": 87
  },
  {
    "x": 160,
    "y": 736,
    "density": 89
  },
  {
    "x": 224,
    "y": 32,
    "density": 80
  },
  {
    "x": 224,
    "y": 96,
    "density": 100
  },
  {
    "x": 224,
    "y": 160,
    "density": 86
  },
  {
    "x": 224,
    "y": 224,
    "density": 102
  },
  {
    "x": 224,
    "y": 288,
    "density": 116
  },
  {
    "x": 224,
    "y": 352,
    "density": 120
  },
  {
    "x": 224,
    "y": 416,
    "density": 98
  },
  {
    "x": 224,
    "y": 480,
    "density": 94
  },
  {
    "x": 224,
    "y": 544,
    "density": 104
  },
  {
    "x": 224,
    "y": 608,
    "density": 98
  },
  {
    "x": 224,
    "y": 672,
    "density": 87
  },
  {
    "x": 224,
    "y": 736,
    "density": 72
  },
  {
    "x": 288,
    "y": 32,
    "density": 100
  },
  {
    "x": 288,
    "y": 96,
    "density": 103
  },
  {
    "x": 288,
    "y": 160,
    "density": 117
  },
  {
    "x": 288,
    "y": 224,
    "density": 124
  },
  {
    "x": 288,
    "y": 288,
    "density": 128
  },
  {
    "x": 288,
    "y": 352,
    "density": 115
  },
  {
    "x": 288,
    "y": 416,
    "density": 111
  },
  {
    "x": 288,
    "y": 480,
    "density": 129
  },
  {
    "x": 288,
    "y": 544,
    "density": 122
  },
  {
    "x": 288,
    "y": 608,
    "density": 89
  },
  {
    "x": 288,
    "y": 672,
    "density": 89
  },
  {
    "x": 288,
    "y": 736,
    "density": 82
  },
  {
    "x": 352,
    "y": 32,
    "density": 96
  },
  {
    "x": 352,
    "y": 96,
    "density": 113
  },
  {
    "x": 352,
    "y": 160,
    "density": 108
  },
  {
    "x": 352,
    "y": 224,
    "density": 124
  },
  {
    "x": 352,
    "y": 288,
    "density": 125
  },
  {
    "x": 352,
    "y": 352,
    "density": 151
  },
  {
    "x": 352,
    "y": 416,
    "density": 151
  },
  {
    "x": 352,
    "y": 480,
    "density": 141
  },
  {
    "x": 352,
    "y": 544,
    "density": 117
  },
  {
    "x": 352,
    "y": 608,
    "density": 109
  },
  {
    "x": 352,
    "y": 672,
    "density": 93
  },
  {
    "x": 352,
    "y": 736,
    "density": 71
  },
  {
    "x": 416,
    "y": 32,
    "density": 114
  },
  {
    "x": 416,
    "y": 96,
    "density": 108
  },
  {
    "x": 416,
    "y": 160,
    "density": 139
  },
  {
    "x": 416,
    "y": 224,
    "density": 154
  },
  {
    "x": 416,
    "y": 288,
    "density": 149
  },
  {
    "x": 416,
    "y": 352,
    "density": 153
  },
  {
    "x": 416,
    "y": 416,
    "density": 152
  },
  {
    "x": 416,
    "y": 480,
    "density": 146
  },
  {
    "x": 416,
    "y": 544,
    "density": 141
  },
  {
    "x": 416,
    "y": 608,
    "density": 105
  },
  {
    "x": 416,
    "y": 672,
    "density": 99
  },
  {
    "x": 416,
    "y": 736,
    "density": 84
  },
  {
    "x": 480,
    "y": 32,
    "density": 119
  },
  {
    "x": 480,
    "y": 96,
    "density": 138
  },
  {
    "x": 480,
    "y": 160,
    "density": 156
  },
  {
    "x": 480,
    "y": 224,
    "density": 162
  },
  {
    "x": 480,
    "y": 288,
    "density": 162
  },
  {
    "x": 480,
    "y": 352,
    "density": 164
  },
  {
    "x": 480,
    "y": 416,
    "density": 171
  },
  {
    "x": 480,
    "y": 480,
    "density": 157
  },
  {
    "x": 480,
    "y": 544,
    "density": 152
  },
  {
    "x": 480,
    "y": 608,
    "density": 115
  },
  {
    "x": 480,
    "y": 672,
    "density": 95
  },
  {
    "x": 480,
    "y": 736,
    "density": 83
  },
  {
    "x": 544,
    "y": 32,
    "density": 127
  },
  {
    "x": 544,
    "y": 96,
    "density": 129
  },
  {
    "x": 544,
    "y": 160,
    "density": 138
  },
  {
    "x": 544,
    "y": 224,
    "density": 155
  },
  {
    "x": 544,
    "y": 288,
    "density": 166
  },
  {
    "x": 544,
    "y": 352,
    "density": 195
  },
  {
    "x": 544,
    "y": 416,
    "density": 166
  },
  {
    "x": 544,
    "y": 480,
    "density": 151
  },
  {
    "x": 544,
    "y": 544,
    "density": 146
  },
  {
    "x": 544,
    "y": 608,
    "density": 137
  },
  {
    "x": 544,
    "y": 672,
    "density": 120
  },
  {
    "x": 544,
    "y": 736,
    "density": 94
  },
  {
    "x": 608,
    "y": 32,
    "density": 116
  },
  {
    "x": 608,
    "y": 96,
    "density": 121
  },
  {
    "x": 608,
    "y": 160,
    "density": 153
  },
  {
    "x": 608,
    "y": 224,
    "density": 157
  },
  {
    "x": 608,
    "y": 288,
    "density": 165
  },
  {
    "x": 608,
    "y": 352,
    "density": 182
  },
  {
    "x": 608,
    "y": 416,
    "density": 178
  },
  {
    "x": 608,
    "y": 480,
    "density": 176
  },
  {
    "x": 608,
    "y": 544,
    "density": 132
  },
  {
    "x": 608,
    "y": 608,
    "density": 139
  },
  {
    "x": 608,
    "y": 672,
    "density": 110
  },
  {
    "x": 608,
    "y": 736,
    "density": 94
  },
  {
    "x": 672,
    "y": 32,
    "density": 110
  },
  {
    "x": 672,
    "y": 96,
    "density": 121
  },
  {
    "x": 672,
    "y": 160,
    "density": 146
  },
  {
    "x": 672,
    "y": 224,
    "density": 146
  },
  {
    "x": 672,
    "y": 288,
    "density": 155
  },
  {
    "x": 672,
    "y": 352,
    "density": 161
  },
  {
    "x": 672,
    "y": 416,
    "density": 168
  },
  {
    "x": 672,
    "y": 480,
    "density": 150
  },
  {
    "x": 672,
    "y": 544,
    "density": 153
  },
  {
    "x": 672,
    "y": 608,
    "density": 136
  },
  {
    "x": 672,
    "y": 672,
    "density": 99
  },
  {
    "x": 672,
    "y": 736,
    "density": 99
  },
  {
    "x": 736,
    "y": 32,
    "density": 109
  },
  {
    "x": 736,
    "y": 96,
    "density": 127
  },
  {
    "x": 736,
    "y": 160,
    "density": 128
  },
  {
    "x": 736,
    "y": 224,
    "density": 158
  },
  {
    "x": 736,
    "y": 288,
    "density": 161
  },
  {
    "x": 736,
    "y": 352,
    "density": 161
  },
  {
    "x": 736,
    "y": 416,
    "density": 151
  },
  {
    "x": 736,
    "y": 480,
    "density": 140
  },
  {
    "x": 736,
    "y": 544,
    "density": 139
  },
  {
    "x": 736,
    "y": 608,
    "density": 114
  },
  {
    "x": 736,
    "y": 672,
    "density": 108
  },
  {
    "x": 736,
    "y": 736,
    "density": 80
  },
  {
    "x": 800,
    "y": 32,
    "density": 110
  },
  {
    "x": 800,
    "y": 96,
    "density": 116
  },
  {
    "x": 800,
    "y": 160,
    "density": 115
  },
  {
    "x": 800,
    "y": 224,
    "density": 136
  },
  {
    "x": 800,
    "y": 288,
    "density": 142
  },
  {
    "x": 800,
    "y": 352,
    "density": 154
  },
  {
    "x": 800,
    "y": 416,
    "density": 150
  },
  {
    "x": 800,
    "y": 480,
    "density": 141
  },
  {
    "x": 800,
    "y": 544,
    "density": 117
  },
  {
    "x": 800,
    "y": 608,
    "density": 96
  },
  {
    "x": 800,
    "y": 672,
    "density": 105
  },
  {
    "x": 800,
    "y": 736,
    "density": 76
  },
  {
    "x": 864,
    "y": 32,
    "density": 81
  },
  {
    "x": 864,
    "y": 96,
    "density": 91
  },
  {
    "x": 864,
    "y": 160,
    "density": 104
  },
  {
    "x": 864,
    "y": 224,
    "density": 109
  },
  {
    "x": 864,
    "y": 288,
    "density": 130
  },
  {
    "x": 864,
    "y": 352,
    "density": 119
  },
  {
    "x": 864,
    "y": 416,
    "density": 124
  },
  {
    "x": 864,
    "y": 480,
    "density": 118
  },
  {
    "x": 864,
    "y": 544,
    "density": 105
  },
  {
    "x": 864,
    "y": 608,
    "density": 84
  },
  {
    "x": 864,
    "y": 672,
    "density": 82
  },
  {
    "x": 864,
    "y": 736,
    "density": 89
  },
  {
    "x": 928,
    "y": 32,
    "density": 80
  },
  {
    "x": 928,
    "y": 96,
    "density": 75
  },
  {
    "x": 928,
    "y": 160,
    "density": 87
  },
  {
    "x": 928,
    "y": 224,
    "density": 112
  },
  {
    "x": 928,
    "y": 288,
    "density": 96
  },
  {
    "x": 928,
    "y": 352,
    "density": 96
  },
  {
    "x": 928,
    "y": 416,
    "density": 111
  },
  {
    "x": 928,
    "y": 480,
    "density": 90
  },
  {
    "x": 928,
    "y": 544,
    "density": 90
  },
  {
    "x": 928,
    "y": 608,
    "density": 71
  },
  {
    "x": 928,
    "y": 672,
    "density": 60
  },
  {
    "x": 928,
    "y": 736,
    "density": 81
  },
  {
    "x": 992,
    "y": 32,
    "density": 70
  },
  {
    "x": 992,
    "y": 96,
    "density": 64
  },
  {
    "x": 992,
    "y": 160,
    "density": 71
  },
  {
    "x": 992,
    "y": 224,
    "density": 73
  },
  {
    "x": 992,
    "y": 288,
    "density": 98
  },
  {
    "x": 992,
    "y": 352,
    "density": 76
  },
  {
    "x": 992,
    "y": 416,
    "density": 94
  },
  {
    "x": 992,
    "y": 480,
    "density": 76
  },
  {
    "x": 992,
    "y": 544,
    "density": 88
  },
  {
    "x": 992,
    "y": 608,
    "density": 61
  },
  {
    "x": 992,
    "y": 672,
    "density": 75
  },
  {
    "x": 992,
    "y": 736,
    "density": 71
  }
]
